llm_evaluator/__init__.py
llm_evaluator/compare.py
llm_evaluator/eval.py
sinhala_llm_evaluator-0.3.4.dist-info/METADATA
sinhala_llm_evaluator-0.3.4.dist-info/WHEEL
sinhala_llm_evaluator-0.3.4.dist-info/top_level.txt
sinhala_llm_evaluator-0.3.4.dist-info/RECORD
